hola_mundo_edison/__init__.py
hello_world_edison-0.1.4.dist-info/METADATA
hello_world_edison-0.1.4.dist-info/WHEEL
hello_world_edison-0.1.4.dist-info/top_level.txt
hello_world_edison-0.1.4.dist-info/RECORD
