Metadata-Version: 2.2
Name: hello_world_edison
Version: 0.1.4
Summary: Una librería simple que dice ¡Hola, mundo!
Author-email: Edison <ERAMREG@proteccion.com.co>
Requires-Python: >=3.7
Requires-Dist: numpy
